{
    "bookId": "bg",
    "chapter": 18,
    "verse": 70,
    "devanagari": "अध्येष्यते च य इमं धर्म्यं संवादमावयो: ।\nज्ञानयज्ञेन तेनाहमिष्ट: स्यामिति मे मति: ॥ ७० ॥",
    "transliteration": "adhyeṣyate ca ya imaṁ\ndharmyaṁ saṁvādam āvayoḥ\njñāna-yajñena tenāham\niṣṭaḥ syām iti me matiḥ",
    "synonyms": [
        {
            "word": "adhyeṣyate",
            "meaning": "will study"
        },
        {
            "word": "ca",
            "meaning": "also"
        },
        {
            "word": "yaḥ",
            "meaning": "he"
        },
        {
            "word": "imam",
            "meaning": "this"
        },
        {
            "word": "dharmyam",
            "meaning": "sacred"
        },
        {
            "word": "saṁvādam",
            "meaning": "conversation"
        },
        {
            "word": "āvayoḥ",
            "meaning": "of ours"
        },
        {
            "word": "jñāna",
            "meaning": "knowledge"
        },
        {
            "word": "yajñena",
            "meaning": "by sacrifice"
        },
        {
            "word": "tena",
            "meaning": "by him"
        },
        {
            "word": "aham",
            "meaning": "I"
        },
        {
            "word": "iṣṭaḥ",
            "meaning": "worshiped"
        },
        {
            "word": "syām",
            "meaning": "shall be"
        },
        {
            "word": "iti",
            "meaning": "thus"
        },
        {
            "word": "me",
            "meaning": "My"
        },
        {
            "word": "matiḥ",
            "meaning": "opinion"
        }
    ],
    "translation": "And I declare that he who studies this sacred conversation worships Me by his intelligence.",
    "purport": ""
}